{"resourceType":"SearchParameter","id":"CapabilityStatement-supported-profile","extension":[{"url":"http://hl7.org/fhir/StructureDefinition/structuredefinition-standards-status","valueCode":"trial-use"}],"url":"http://hl7.org/fhir/SearchParameter/CapabilityStatement-supported-profile","version":"4.0.1","name":"supported-profile","status":"draft","experimental":false,"date":"2019-11-01T09:29:23+11:00","publisher":"Health Level Seven International (FHIR Infrastructure)","contact":[{"telecom":[{"system":"url","value":"http://hl7.org/fhir"}]},{"telecom":[{"system":"url","value":"http://www.hl7.org/Special/committees/fiwg/index.cfm"}]}],"description":"Profiles for use cases supported","code":"supported-profile","base":["CapabilityStatement"],"type":"reference","expression":"CapabilityStatement.rest.resource.supportedProfile","xpath":"f:CapabilityStatement/f:rest/f:resource/f:supportedProfile","xpathUsage":"normal","target":["StructureDefinition"]}