{"resourceType":"CodeSystem","id":"v2-0007","meta":{"profile":["http://hl7.org/fhir/StructureDefinition/shareablecodesystem"]},"language":"en","extension":[{"url":"http://hl7.org/fhir/StructureDefinition/structuredefinition-standards-status","valueCode":"external"},{"url":"http://hl7.org/fhir/StructureDefinition/structuredefinition-fmm","valueInteger":0}],"url":"http://terminology.hl7.org/CodeSystem/v2-0007","identifier":[{"system":"urn:ietf:rfc:3986","value":"urn:oid:2.16.840.1.113883.18.9"}],"version":"2.9","name":"v2.0007","title":"v2 ADMISSION TYPE","status":"active","experimental":false,"publisher":"HL7, Inc","contact":[{"telecom":[{"system":"url","value":"http://hl7.org"}]}],"description":"FHIR Value set/code system definition for HL7 v2 table 0007 ( ADMISSION TYPE)","content":"complete","concept":[{"code":"A","display":"Accident","designation":[{"language":"de","use":{"system":"http://terminology.hl7.org/CodeSystem/designation-usage","code":"display"},"value":"Unfall / Notarztwagen"},{"language":"nl","use":{"system":"http://terminology.hl7.org/CodeSystem/designation-usage","code":"display"},"value":"Ongeluk"}]},{"code":"C","display":"Elective","designation":[{"language":"de","use":{"system":"http://terminology.hl7.org/CodeSystem/designation-usage","code":"display"},"value":"wahlfreie Aufnahme"},{"language":"nl","use":{"system":"http://terminology.hl7.org/CodeSystem/designation-usage","code":"display"},"value":"Eigen keuze"}]},{"code":"E","display":"Emergency","designation":[{"language":"de","use":{"system":"http://terminology.hl7.org/CodeSystem/designation-usage","code":"display"},"value":"Notfall ohne Einweisung"},{"language":"nl","use":{"system":"http://terminology.hl7.org/CodeSystem/designation-usage","code":"display"},"value":"Spoed"}]},{"code":"L","display":"Labor and Delivery","designation":[{"language":"de","use":{"system":"http://terminology.hl7.org/CodeSystem/designation-usage","code":"display"},"value":"Entbindung / Geburt"},{"language":"nl","use":{"system":"http://terminology.hl7.org/CodeSystem/designation-usage","code":"display"},"value":"Geboorte en bevalling"}]},{"code":"N","display":"Newborn (Birth in healthcare facility)","designation":[{"language":"de","use":{"system":"http://terminology.hl7.org/CodeSystem/designation-usage","code":"display"},"value":"Neugeborenes"},{"language":"nl","use":{"system":"http://terminology.hl7.org/CodeSystem/designation-usage","code":"display"},"value":"Nieuwgeborene (geboorte in zorginstelling)"}]},{"code":"R","display":"Routine","designation":[{"language":"de","use":{"system":"http://terminology.hl7.org/CodeSystem/designation-usage","code":"display"},"value":"Normalaufnahme"},{"language":"nl","use":{"system":"http://terminology.hl7.org/CodeSystem/designation-usage","code":"display"},"value":"Routine"}]},{"code":"U","display":"Urgent","designation":[{"language":"de","use":{"system":"http://terminology.hl7.org/CodeSystem/designation-usage","code":"display"},"value":"dringliche Aufnahme"},{"language":"nl","use":{"system":"http://terminology.hl7.org/CodeSystem/designation-usage","code":"display"},"value":"Urgent"}]}]}