{"resourceType":"CodeSystem","id":"v2-0417","meta":{"profile":["http://hl7.org/fhir/StructureDefinition/shareablecodesystem"]},"language":"en","extension":[{"url":"http://hl7.org/fhir/StructureDefinition/structuredefinition-standards-status","valueCode":"external"},{"url":"http://hl7.org/fhir/StructureDefinition/structuredefinition-fmm","valueInteger":0}],"url":"http://terminology.hl7.org/CodeSystem/v2-0417","identifier":[{"system":"urn:ietf:rfc:3986","value":"urn:oid:2.16.840.1.113883.18.259"}],"version":"2.9","name":"v2.0417","title":"v2 Tissue type code","status":"active","experimental":false,"publisher":"HL7, Inc","contact":[{"telecom":[{"system":"url","value":"http://hl7.org"}]}],"description":"FHIR Value set/code system definition for HL7 v2 table 0417 ( Tissue type code)","content":"complete","concept":[{"code":"0","display":"No tissue expected"},{"code":"1","display":"Insufficient Tissue"},{"code":"2","display":"Not abnormal"},{"code":"3","display":"Abnormal-not categorized"},{"code":"4","display":"Mechanical abnormal"},{"code":"5","display":"Growth alteration"},{"code":"6","display":"Degeneration & necrosis"},{"code":"7","display":"Non-acute inflammation"},{"code":"8","display":"Non-malignant neoplasm"},{"code":"9","display":"Malignant neoplasm"},{"code":"B","display":"Basal cell carcinoma"},{"code":"C","display":"Carcinoma-unspecified type"},{"code":"G","display":"Additional tissue required"}]}