{"resourceType":"CodeSystem","id":"audit-event-type","meta":{"lastUpdated":"2017-04-19T07:44:43.294+10:00","profile":["http://hl7.org/fhir/StructureDefinition/shareablecodesystem"]},"text":{"status":"generated","div":"<div xmlns=\"http://www.w3.org/1999/xhtml\">\n            <h2>Audit Event ID</h2>\n            <div>\n              <p>Event Types for Audit Events - defined by DICOM with some FHIR specific additions.</p>\n\n            </div>\n            <p>\n              <b>Copyright Statement:</b> These codes are excerpted from Digital Imaging and Communications in Medicine (DICOM) Standard, Part 16: Content Mapping Resource, Copyright © 2011 by the National Electrical Manufacturers Association.\n            </p>\n            <p>This code system http://hl7.org/fhir/audit-event-type defines the following codes:</p>\n            <table class=\"codes\">\n              <tr>\n                <td>\n                  <b>Code</b>\n                </td>\n                <td>\n                  <b>Display</b>\n                </td>\n                <td>\n                  <b>Definition</b>\n                </td>\n              </tr>\n              <tr>\n                <td>rest\n                  <a name=\"audit-event-type-rest\"> </a>\n                </td>\n                <td>RESTful Operation</td>\n                <td>Audit Event: Execution of a RESTful operation as defined by FHIR.</td>\n              </tr>\n            </table>\n          </div>"},"extension":[{"url":"http://hl7.org/fhir/StructureDefinition/structuredefinition-ballot-status","valueString":"Informative"},{"url":"http://hl7.org/fhir/StructureDefinition/structuredefinition-fmm","valueInteger":3},{"url":"http://hl7.org/fhir/StructureDefinition/structuredefinition-wg","valueCode":"sec"}],"url":"http://hl7.org/fhir/audit-event-type","identifier":{"system":"urn:ietf:rfc:3986","value":"urn:oid:2.16.840.1.113883.4.642.1.456"},"version":"20150326","name":"Audit Event ID","status":"active","experimental":true,"date":"2015-03-26T00:00:00+11:00","publisher":"NEMA/DICOM","description":"Event Types for Audit Events - defined by DICOM with some FHIR specific additions.","copyright":"These codes are excerpted from Digital Imaging and Communications in Medicine (DICOM) Standard, Part 16: Content Mapping Resource, Copyright © 2011 by the National Electrical Manufacturers Association.","caseSensitive":true,"valueSet":"http://hl7.org/fhir/ValueSet/audit-event-type","content":"complete","concept":[{"code":"rest","display":"RESTful Operation","definition":"Audit Event: Execution of a RESTful operation as defined by FHIR."}]}