{"resourceType":"DataElement","id":"ValueSet.expansion.parameter.name","meta":{"lastUpdated":"2017-04-19T07:44:43.294+10:00"},"url":"http://hl7.org/fhir/DataElement/ValueSet.expansion.parameter.name","status":"draft","experimental":true,"stringency":"fully-specified","element":[{"id":"ValueSet.expansion.parameter.name","path":"ValueSet.expansion.parameter.name","short":"Name as assigned by the server","definition":"The name of the parameter.","comment":"The names are assigned at the discretion of the server.","min":1,"max":"1","type":[{"code":"string"}]}]}