{"resourceType":"DataElement","id":"Device.contact","meta":{"lastUpdated":"2017-04-19T07:44:43.294+10:00"},"url":"http://hl7.org/fhir/DataElement/Device.contact","status":"draft","experimental":true,"stringency":"fully-specified","element":[{"id":"Device.contact","path":"Device.contact","short":"Details for human/organization for support","definition":"Contact details for an organization or a particular human that is responsible for the device.","comment":"used for troubleshooting etc.","min":0,"max":"*","type":[{"code":"ContactPoint"}],"mapping":[{"identity":"rim","map":".scopedRole[typeCode=CON].player"},{"identity":"w5","map":"who.source"}]}]}