{"resourceType":"DataElement","id":"Medication.image","meta":{"lastUpdated":"2017-04-19T07:44:43.294+10:00"},"url":"http://hl7.org/fhir/DataElement/Medication.image","status":"draft","experimental":true,"stringency":"fully-specified","element":[{"id":"Medication.image","path":"Medication.image","short":"Picture of the medication","definition":"Photo(s) or graphic representation(s) of the medication.","requirements":"Note that \"image\" is only applicable when the medication.code represents a physical item (e.g. Amoxil 250 mg capsule) and not an abstract item (e.g. amoxicillin 250 mg).","min":0,"max":"*","type":[{"code":"Attachment"}],"mapping":[{"identity":"rim","map":".participation[typeCode=SUBJ].role[classCode=MANU],source[classCode=OBS,moodCode=EVN,code=\"type of image\"].value(ED.image)"}]}]}