{"resourceType":"DataElement","id":"HealthcareService.coverageArea","meta":{"lastUpdated":"2017-04-19T07:44:43.294+10:00"},"url":"http://hl7.org/fhir/DataElement/HealthcareService.coverageArea","status":"draft","experimental":true,"stringency":"fully-specified","element":[{"id":"HealthcareService.coverageArea","path":"HealthcareService.coverageArea","short":"Location(s) service is inteded for/available to","definition":"The location(s) that this service is available to (not where the service is provided).","comment":"The locations referenced by the coverage area can include both specific locations, including areas, and also conceptual domains too (mode = kind), such as a physical area (tri-state area) and some other attribute (covered by Example Care Organization). These types of Locations are often not managed by any specific organization. This could also include generic locations such as \"in-home\".","min":0,"max":"*","type":[{"code":"Reference","targetProfile":"http://hl7.org/fhir/StructureDefinition/Location"}],"mapping":[{"identity":"rim","map":".location.role[classCode=SDLOC].subjectOf.A_SpatialCoordinate"}]}]}