{"resourceType":"DataElement","id":"ImplementationGuide.page.source","meta":{"lastUpdated":"2015-10-24T07:41:03.495+11:00"},"url":"http://hl7.org/fhir/DataElement/ImplementationGuide.page.source","status":"draft","experimental":true,"stringency":"fully-specified","element":[{"path":"ImplementationGuide.page.source","short":"Where to find that page","definition":"The source address for the page.","comments":"The publishing tool will autogenerate source for list (source = n/a), and inject included implementations for include (source = uri of guide to include).","min":1,"max":"1","type":[{"code":"uri"}],"isSummary":true}]}