{"resourceType":"DataElement","id":"Composition.attester.mode","meta":{"lastUpdated":"2015-10-24T07:41:03.495+11:00"},"url":"http://hl7.org/fhir/DataElement/Composition.attester.mode","status":"draft","experimental":true,"stringency":"fully-specified","element":[{"path":"Composition.attester.mode","short":"personal | professional | legal | official","definition":"The type of attestation the authenticator offers.","comments":"Use more than one code where a single attester has more than one mode (professional and legal are often paired).","requirements":"Indicates the level of authority of the attestation.","min":1,"max":"*","type":[{"code":"code"}],"isSummary":true,"binding":{"strength":"required","description":"The way in which a person authenticated a composition.","valueSetReference":{"reference":"http://hl7.org/fhir/ValueSet/composition-attestation-mode"}},"mapping":[{"identity":"cda","map":"implied by .authenticator/.legalAuthenticator"},{"identity":"rim","map":"unique(./modeCode)"}]}]}