{"resourceType":"SearchParameter","id":"ConceptMap-target","url":"http://hl7.org/fhir/SearchParameter/ConceptMap-target","name":"target","publisher":"Health Level Seven International (Vocabulary)","contact":[{"telecom":[{"system":"other","value":"http://hl7.org/fhir"}]},{"telecom":[{"system":"other","value":"http://www.hl7.org/Special/committees/Vocab/index.cfm"}]}],"date":"2015-10-24T07:41:03+11:00","code":"target","base":"ConceptMap","type":"reference","description":"Provides context to the mappings","xpath":"f:ConceptMap/f:targetUri | f:ConceptMap/f:targetReference","xpathUsage":"normal","target":["ValueSet","StructureDefinition"]}